Metadata-Version: 2.0
Name: odoo8-addon-base-construction-architect
Version: 8.0.0.1.0
Summary: Identify partners as architects.
Home-page: UNKNOWN
Author: UNKNOWN
Author-email: UNKNOWN
License: UNKNOWN
Platform: UNKNOWN
Requires-Dist: odoo (<9.0a,>=8.0a)
Classifier: Programming Language :: Python :: 2.7
Classifier: Framework :: Odoo
